matrix_chandramdutta/__init__.py
matrix_chandramdutta/matrix.py
matrix_chandramdutta-1.1.3.dist-info/METADATA
matrix_chandramdutta-1.1.3.dist-info/WHEEL
matrix_chandramdutta-1.1.3.dist-info/licenses/LICENSE
matrix_chandramdutta-1.1.3.dist-info/RECORD
