Metadata-Version: 2.1
Name: matrix_chandramdutta
Version: 1.1.3
Summary: The Python Library for managing your matrix (◕‿↼)
Project-URL: Homepage, https://github.com/Chandram-Dutta/matrix
Project-URL: Bug Tracker, https://github.com/Chandram-Dutta/matrix/issues
Author-email: Chandram Dutta <chandramdutta2004@gmail.com>
License-File: LICENSE
Classifier: License :: OSI Approved :: MIT License
Classifier: Operating System :: OS Independent
Classifier: Programming Language :: Python :: 3
Requires-Python: >=3.7
